pears/__init__.py
pears/pears.py
pears-0.1.10.dist-info/LICENSE-APACHE
pears-0.1.10.dist-info/LICENSE-MIT
pears-0.1.10.dist-info/METADATA
pears-0.1.10.dist-info/WHEEL
pears-0.1.10.dist-info/RECORD
